{
  "company": "HeyDoctor (GoodRx Care)",
  "website": "https://www.goodrx.com/care",
  "channels": {
    "website": "https://www.goodrx.com/care",
    "linkedinCompanySearch": "https://www.linkedin.com/search/results/companies/?keywords=HeyDoctor%20(GoodRx%20Care)"
  },
  "assets": { "logo": "logo.png", "logoSource": "favicon via google s2 service, domain goodrx.com", "fetched": "2026-07-19" },
  "policy": "company-level public assets only; no personal data of founders stored (consent-gated per system design)"
}
